MANIFEST.in
setup.py
antfin/__init__.py
antfin/antfin.py
antfin.egg-info/PKG-INFO
antfin.egg-info/SOURCES.txt
antfin.egg-info/dependency_links.txt
antfin.egg-info/top_level.txt