Metadata-Version: 1.0
Name: antfin
Version: 0.0.1
Summary: MyTest API
Home-page: UNKNOWN
Author: Derek
Author-email: dingo0927@126.com
License: UNKNOWN
Platform: UNKNOWN
